[
    {
        "content": [
            {
                "x": 10.23041474654378,
                "y": 4.4239631336405605
            },
            {
                "x": 1063.1336405529953,
                "y": 4.4239631336405605
            },
            {
                "x": 1063.1336405529953,
                "y": 274.2857142857143
            },
            {
                "x": 10.23041474654378,
                "y": 274.2857142857143
            }
        ],
        "rectMask": {
            "xMin": 10.23041474654378,
            "yMin": 4.4239631336405605,
            "width": 1052.9032258064517,
            "height": 269.86175115207374
        },
        "labels": {
            "labelName": "sky",
            "labelColor": "#75fffa",
            "labelColorRGB": "117,255,250",
            "visibility": true
        },
        "labelLocation": {
            "x": 536.6820276497697,
            "y": 139.35483870967744
        },
        "contentType": "rect"
    },
    {
        "content": [
            {
                "x": 339.815668202765,
                "y": 287.55760368663596
            },
            {
                "x": 1067.5576036866357,
                "y": 287.55760368663596
            },
            {
                "x": 1067.5576036866357,
                "y": 449.0322580645161
            },
            {
                "x": 339.815668202765,
                "y": 449.0322580645161
            }
        ],
        "rectMask": {
            "xMin": 339.815668202765,
            "yMin": 287.55760368663596,
            "width": 727.741935483871,
            "height": 161.47465437788017
        },
        "labels": {
            "labelName": "sky",
            "labelColor": "#75fffa",
            "labelColorRGB": "117,255,250",
            "visibility": true
        },
        "labelLocation": {
            "x": 703.6866359447005,
            "y": 368.29493087557603
        },
        "contentType": "rect"
    },
    {
        "content": [
            {
                "x": 611.889400921659,
                "y": 473.3640552995392
            },
            {
                "x": 1080,
                "y": 473.3640552995392
            },
            {
                "x": 1080,
                "y": 568.479262672811
            },
            {
                "x": 611.889400921659,
                "y": 568.479262672811
            }
        ],
        "rectMask": {
            "xMin": 611.889400921659,
            "yMin": 473.3640552995392,
            "width": 468.110599078341,
            "height": 95.1152073732719
        },
        "labels": {
            "labelName": "sky",
            "labelColor": "#75fffa",
            "labelColorRGB": "117,255,250",
            "visibility": true
        },
        "labelLocation": {
            "x": 845.9447004608295,
            "y": 520.9216589861751
        },
        "contentType": "rect"
    },
    {
        "content": [
            {
                "x": 815.3917050691244,
                "y": 606.0829493087557
            },
            {
                "x": 1076.405529953917,
                "y": 606.0829493087557
            },
            {
                "x": 1076.405529953917,
                "y": 738.8018433179724
            },
            {
                "x": 815.3917050691244,
                "y": 738.8018433179724
            }
        ],
        "rectMask": {
            "xMin": 815.3917050691244,
            "yMin": 606.0829493087557,
            "width": 261.0138248847926,
            "height": 132.7188940092166
        },
        "labels": {
            "labelName": "building",
            "labelColor": "#ff1c59",
            "labelColorRGB": "255,28,89",
            "visibility": true
        },
        "labelLocation": {
            "x": 945.8986175115208,
            "y": 672.442396313364
        },
        "contentType": "rect"
    },
    {
        "content": [
            {
                "x": 202.67281105990784,
                "y": 608.294930875576
            },
            {
                "x": 806.5437788018434,
                "y": 608.294930875576
            },
            {
                "x": 806.5437788018434,
                "y": 1159.078341013825
            },
            {
                "x": 202.67281105990784,
                "y": 1159.078341013825
            }
        ],
        "rectMask": {
            "xMin": 202.67281105990784,
            "yMin": 608.294930875576,
            "width": 603.8709677419355,
            "height": 550.7834101382489
        },
        "labels": {
            "labelName": "palm tree",
            "labelColor": "#52b7ff",
            "labelColorRGB": "82,183,255",
            "visibility": true
        },
        "labelLocation": {
            "x": 504.60829493087556,
            "y": 883.6866359447005
        },
        "contentType": "rect"
    },
    {
        "content": [
            {
                "x": 76.58986175115207,
                "y": 1030.7834101382489
            },
            {
                "x": 187.1889400921659,
                "y": 1030.7834101382489
            },
            {
                "x": 187.1889400921659,
                "y": 1141.3824884792627
            },
            {
                "x": 76.58986175115207,
                "y": 1141.3824884792627
            }
        ],
        "rectMask": {
            "xMin": 76.58986175115207,
            "yMin": 1030.7834101382489,
            "width": 110.59907834101381,
            "height": 110.59907834101381
        },
        "labels": {
            "labelName": "Ground",
            "labelColor": "#691e00",
            "labelColorRGB": "105,30,0",
            "visibility": true
        },
        "labelLocation": {
            "x": 131.889400921659,
            "y": 1086.0829493087558
        },
        "contentType": "rect"
    },
    {
        "content": [
            {
                "x": 43.41013824884793,
                "y": 1203.3179723502303
            },
            {
                "x": 726.912442396313,
                "y": 1203.3179723502303
            },
            {
                "x": 726.912442396313,
                "y": 1395.7603686635941
            },
            {
                "x": 43.41013824884793,
                "y": 1395.7603686635941
            }
        ],
        "rectMask": {
            "xMin": 43.41013824884793,
            "yMin": 1203.3179723502303,
            "width": 683.5023041474655,
            "height": 192.44239631336404
        },
        "labels": {
            "labelName": "small shrub",
            "labelColor": "#6fd13e",
            "labelColorRGB": "111,209,62",
            "visibility": true
        },
        "labelLocation": {
            "x": 385.16129032258067,
            "y": 1299.5391705069123
        },
        "contentType": "rect"
    },
    {
        "content": [
            {
                "x": 85.43778801843318,
                "y": 1466.5437788018432
            },
            {
                "x": 689.3087557603686,
                "y": 1466.5437788018432
            },
            {
                "x": 689.3087557603686,
                "y": 1581.5668202764978
            },
            {
                "x": 85.43778801843318,
                "y": 1581.5668202764978
            }
        ],
        "rectMask": {
            "xMin": 85.43778801843318,
            "yMin": 1466.5437788018432,
            "width": 603.8709677419355,
            "height": 115.02304147465438
        },
        "labels": {
            "labelName": "divider",
            "labelColor": "#f7ff00",
            "labelColorRGB": "247,255,0",
            "visibility": true
        },
        "labelLocation": {
            "x": 387.37327188940094,
            "y": 1524.0552995391704
        },
        "contentType": "rect"
    },
    {
        "content": [
            {
                "x": 841.9354838709677,
                "y": 1017.5115207373271
            },
            {
                "x": 952.5345622119816,
                "y": 1017.5115207373271
            },
            {
                "x": 952.5345622119816,
                "y": 1128.110599078341
            },
            {
                "x": 841.9354838709677,
                "y": 1128.110599078341
            }
        ],
        "rectMask": {
            "xMin": 841.9354838709677,
            "yMin": 1017.5115207373271,
            "width": 110.59907834101381,
            "height": 110.59907834101381
        },
        "labels": {
            "labelName": "Ground",
            "labelColor": "#691e00",
            "labelColorRGB": "105,30,0",
            "visibility": true
        },
        "labelLocation": {
            "x": 897.2350230414746,
            "y": 1072.811059907834
        },
        "contentType": "rect"
    },
    {
        "content": [
            {
                "x": 12.442396313364055,
                "y": 1639.078341013825
            },
            {
                "x": 729.1244239631336,
                "y": 1639.078341013825
            },
            {
                "x": 729.1244239631336,
                "y": 1893.456221198157
            },
            {
                "x": 12.442396313364055,
                "y": 1893.456221198157
            }
        ],
        "rectMask": {
            "xMin": 12.442396313364055,
            "yMin": 1639.078341013825,
            "width": 716.6820276497695,
            "height": 254.3778801843318
        },
        "labels": {
            "labelName": "road",
            "labelColor": "#595959",
            "labelColorRGB": "89,89,89",
            "visibility": true
        },
        "labelLocation": {
            "x": 370.78341013824877,
            "y": 1766.2672811059908
        },
        "contentType": "rect"
    },
    {
        "content": [
            {
                "x": 733.5483870967739,
                "y": 1324.9769585253457
            },
            {
                "x": 1058.7096774193549,
                "y": 1324.9769585253457
            },
            {
                "x": 1058.7096774193549,
                "y": 1900.0921658986178
            },
            {
                "x": 733.5483870967739,
                "y": 1900.0921658986178
            }
        ],
        "rectMask": {
            "xMin": 733.5483870967739,
            "yMin": 1324.9769585253457,
            "width": 325.16129032258067,
            "height": 575.1152073732719
        },
        "labels": {
            "labelName": "Pic-in-Pic",
            "labelColor": "#000000",
            "labelColorRGB": "0,0,0",
            "visibility": true
        },
        "labelLocation": {
            "x": 896.1290322580643,
            "y": 1612.5345622119817
        },
        "contentType": "rect"
    },
    {
        "content": [
            {
                "x": 963.5586095829025,
                "y": 762.0465334233872
            },
            {
                "x": 1072.7968971674825,
                "y": 762.0465334233872
            },
            {
                "x": 1072.7968971674825,
                "y": 898.343846372955
            },
            {
                "x": 963.5586095829025,
                "y": 898.343846372955
            }
        ],
        "rectMask": {
            "xMin": 963.5586095829025,
            "yMin": 762.0465334233872,
            "width": 109.23828758458012,
            "height": 136.29731294956787
        },
        "labels": {
            "labelName": "palm tree",
            "labelColor": "#52b7ff",
            "labelColorRGB": "82,183,255",
            "visibility": true
        },
        "labelLocation": {
            "x": 1018.1777533751925,
            "y": 830.1951898981712
        },
        "contentType": "rect"
    },
    {
        "content": [
            {
                "x": 811.2263186392679,
                "y": 815.1623980287336
            },
            {
                "x": 939.5061425918021,
                "y": 815.1623980287336
            },
            {
                "x": 939.5061425918021,
                "y": 926.4050578625721
            },
            {
                "x": 811.2263186392679,
                "y": 926.4050578625721
            }
        ],
        "rectMask": {
            "xMin": 811.2263186392679,
            "yMin": 815.1623980287336,
            "width": 128.27982395253446,
            "height": 111.24265983383849
        },
        "labels": {
            "labelName": "palm tree",
            "labelColor": "#52b7ff",
            "labelColorRGB": "82,183,255",
            "visibility": true
        },
        "labelLocation": {
            "x": 875.3662306155352,
            "y": 870.7837279456528
        },
        "contentType": "rect"
    }
]