[
    {
        "content": [
            {
                "x": 1.3824884792626728,
                "y": 4.423963133640553
            },
            {
                "x": 1080,
                "y": 4.423963133640553
            },
            {
                "x": 1080,
                "y": 402.5806451612903
            },
            {
                "x": 1.3824884792626728,
                "y": 402.5806451612903
            }
        ],
        "rectMask": {
            "xMin": 1.3824884792626728,
            "yMin": 4.423963133640553,
            "width": 1078.6175115207373,
            "height": 398.15668202764977
        },
        "labels": {
            "labelName": "sky",
            "labelColor": "#75fffa",
            "labelColorRGB": "117,255,250",
            "visibility": true
        },
        "labelLocation": {
            "x": 540.6912442396313,
            "y": 203.50230414746542
        },
        "contentType": "rect"
    },
    {
        "content": [
            {
                "x": 5.806451612903226,
                "y": 579.5391705069125
            },
            {
                "x": 954.7465437788019,
                "y": 579.5391705069125
            },
            {
                "x": 954.7465437788019,
                "y": 1141.3824884792627
            },
            {
                "x": 5.806451612903226,
                "y": 1141.3824884792627
            }
        ],
        "rectMask": {
            "xMin": 5.806451612903226,
            "yMin": 579.5391705069125,
            "width": 948.9400921658986,
            "height": 561.8433179723502
        },
        "labels": {
            "labelName": "big tree",
            "labelColor": "#00420f",
            "labelColorRGB": "0,66,15",
            "visibility": true
        },
        "labelLocation": {
            "x": 480.2764976958525,
            "y": 860.4608294930875
        },
        "contentType": "rect"
    },
    {
        "content": [
            {
                "x": 222.58064516129033,
                "y": 451.2442396313364
            },
            {
                "x": 746.8202764976959,
                "y": 451.2442396313364
            },
            {
                "x": 746.8202764976959,
                "y": 579.5391705069125
            },
            {
                "x": 222.58064516129033,
                "y": 579.5391705069125
            }
        ],
        "rectMask": {
            "xMin": 222.58064516129033,
            "yMin": 451.2442396313364,
            "width": 524.2396313364055,
            "height": 128.29493087557603
        },
        "labels": {
            "labelName": "big tree",
            "labelColor": "#00420f",
            "labelColorRGB": "0,66,15",
            "visibility": true
        },
        "labelLocation": {
            "x": 484.70046082949307,
            "y": 515.3917050691244
        },
        "contentType": "rect"
    },
    {
        "content": [
            {
                "x": 5.806451612903226,
                "y": 488.8479262672811
            },
            {
                "x": 98.70967741935483,
                "y": 488.8479262672811
            },
            {
                "x": 98.70967741935483,
                "y": 572.9032258064516
            },
            {
                "x": 5.806451612903226,
                "y": 572.9032258064516
            }
        ],
        "rectMask": {
            "xMin": 5.806451612903226,
            "yMin": 488.8479262672811,
            "width": 92.90322580645162,
            "height": 84.0552995391705
        },
        "labels": {
            "labelName": "big tree",
            "labelColor": "#00420f",
            "labelColorRGB": "0,66,15",
            "visibility": true
        },
        "labelLocation": {
            "x": 52.25806451612903,
            "y": 530.8755760368663
        },
        "contentType": "rect"
    },
    {
        "content": [
            {
                "x": 293.3640552995392,
                "y": 1145.8064516129032
            },
            {
                "x": 609.6774193548387,
                "y": 1145.8064516129032
            },
            {
                "x": 609.6774193548387,
                "y": 1190.0460829493088
            },
            {
                "x": 293.3640552995392,
                "y": 1190.0460829493088
            }
        ],
        "rectMask": {
            "xMin": 293.3640552995392,
            "yMin": 1145.8064516129032,
            "width": 316.31336405529953,
            "height": 44.23963133640553
        },
        "labels": {
            "labelName": "big tree",
            "labelColor": "#00420f",
            "labelColorRGB": "0,66,15",
            "visibility": true
        },
        "labelLocation": {
            "x": 451.52073732718895,
            "y": 1167.926267281106
        },
        "contentType": "rect"
    },
    {
        "content": [
            {
                "x": 430.5069124423963,
                "y": 1198.89400921659
            },
            {
                "x": 532.258064516129,
                "y": 1198.89400921659
            },
            {
                "x": 532.258064516129,
                "y": 1440
            },
            {
                "x": 430.5069124423963,
                "y": 1440
            }
        ],
        "rectMask": {
            "xMin": 430.5069124423963,
            "yMin": 1198.89400921659,
            "width": 101.75115207373271,
            "height": 241.10599078341014
        },
        "labels": {
            "labelName": "big tree",
            "labelColor": "#00420f",
            "labelColorRGB": "0,66,15",
            "visibility": true
        },
        "labelLocation": {
            "x": 481.38248847926263,
            "y": 1319.447004608295
        },
        "contentType": "rect"
    },
    {
        "content": [
            {
                "x": 968.0184331797235,
                "y": 811.7972350230415
            },
            {
                "x": 1074.1935483870968,
                "y": 811.7972350230415
            },
            {
                "x": 1074.1935483870968,
                "y": 1035.2073732718893
            },
            {
                "x": 968.0184331797235,
                "y": 1035.2073732718893
            }
        ],
        "rectMask": {
            "xMin": 968.0184331797235,
            "yMin": 811.7972350230415,
            "width": 106.17511520737327,
            "height": 223.41013824884791
        },
        "labels": {
            "labelName": "big tree",
            "labelColor": "#00420f",
            "labelColorRGB": "0,66,15",
            "visibility": true
        },
        "labelLocation": {
            "x": 1021.1059907834101,
            "y": 923.5023041474655
        },
        "contentType": "rect"
    },
    {
        "content": [
            {
                "x": 1.3824884792626728,
                "y": 1172.3502304147466
            },
            {
                "x": 227.00460829493088,
                "y": 1172.3502304147466
            },
            {
                "x": 227.00460829493088,
                "y": 1592.626728110599
            },
            {
                "x": 1.3824884792626728,
                "y": 1592.626728110599
            }
        ],
        "rectMask": {
            "xMin": 1.3824884792626728,
            "yMin": 1172.3502304147466,
            "width": 225.6221198156682,
            "height": 420.2764976958525
        },
        "labels": {
            "labelName": "small shrub",
            "labelColor": "#6fd13e",
            "labelColorRGB": "111,209,62",
            "visibility": true
        },
        "labelLocation": {
            "x": 114.19354838709678,
            "y": 1382.4884792626729
        },
        "contentType": "rect"
    },
    {
        "content": [
            {
                "x": 280.0921658986175,
                "y": 1462.1198156682028
            },
            {
                "x": 729.1244239631336,
                "y": 1462.1198156682028
            },
            {
                "x": 729.1244239631336,
                "y": 1900.0921658986174
            },
            {
                "x": 280.0921658986175,
                "y": 1900.0921658986174
            }
        ],
        "rectMask": {
            "xMin": 280.0921658986175,
            "yMin": 1462.1198156682028,
            "width": 449.0322580645161,
            "height": 437.97235023041475
        },
        "labels": {
            "labelName": "Ground",
            "labelColor": "#691e00",
            "labelColorRGB": "105,30,0",
            "visibility": true
        },
        "labelLocation": {
            "x": 504.60829493087556,
            "y": 1681.10599078341
        },
        "contentType": "rect"
    }
]